BlueWhale3_ImageAnalytics-0.6.1-py3.8-nspkg.pth
orangecontrib/imageanalytics/__init__.py
orangecontrib/imageanalytics/i18n_config.py
orangecontrib/imageanalytics/image_embedder.py
orangecontrib/imageanalytics/image_grid.py
orangecontrib/imageanalytics/import_images.py
orangecontrib/imageanalytics/local_embedder.py
orangecontrib/imageanalytics/server_embedder.py
orangecontrib/imageanalytics/locale/imganlytic.en.yml
orangecontrib/imageanalytics/locale/imganlytic.zh.yml
orangecontrib/imageanalytics/tests/__init__.py
orangecontrib/imageanalytics/tests/example_image_0.jpg
orangecontrib/imageanalytics/tests/example_image_1.tiff
orangecontrib/imageanalytics/tests/example_image_2.png
orangecontrib/imageanalytics/tests/test_image_embedder.py
orangecontrib/imageanalytics/tests/test_image_grid.py
orangecontrib/imageanalytics/tests/test_import_images.py
orangecontrib/imageanalytics/utils/__init__.py
orangecontrib/imageanalytics/utils/embedder_utils.py
orangecontrib/imageanalytics/utils/tests/__init__.py
orangecontrib/imageanalytics/utils/tests/test_embedder_utils.py
orangecontrib/imageanalytics/widgets/__init__.py
orangecontrib/imageanalytics/widgets/owimageembedding.py
orangecontrib/imageanalytics/widgets/owimagegrid.py
orangecontrib/imageanalytics/widgets/owimageimport.py
orangecontrib/imageanalytics/widgets/owimageviewer.py
orangecontrib/imageanalytics/widgets/owsaveimages.py
orangecontrib/imageanalytics/widgets/icons/Category-ImageAnalytics.svg
orangecontrib/imageanalytics/widgets/icons/ImageEmbedding.svg
orangecontrib/imageanalytics/widgets/icons/ImageGrid.svg
orangecontrib/imageanalytics/widgets/icons/ImageViewer.svg
orangecontrib/imageanalytics/widgets/icons/ImportImages.svg
orangecontrib/imageanalytics/widgets/icons/SaveImages.svg
orangecontrib/imageanalytics/widgets/tests/__init__.py
orangecontrib/imageanalytics/widgets/tests/test_owimageembedding.py
orangecontrib/imageanalytics/widgets/tests/test_owimagegrid.py
BlueWhale3_ImageAnalytics-0.6.1.dist-info/LICENSE.txt
BlueWhale3_ImageAnalytics-0.6.1.dist-info/METADATA
BlueWhale3_ImageAnalytics-0.6.1.dist-info/WHEEL
BlueWhale3_ImageAnalytics-0.6.1.dist-info/entry_points.txt
BlueWhale3_ImageAnalytics-0.6.1.dist-info/namespace_packages.txt
BlueWhale3_ImageAnalytics-0.6.1.dist-info/top_level.txt
BlueWhale3_ImageAnalytics-0.6.1.dist-info/RECORD
